toolkit/__init__.py
toolkit/__init__.pyi
toolkit/py.typed
toolkit/_func/__init__.py
toolkit/_func/__init__.pyi
toolkit/_func/_kwargs.py
toolkit/_iter/__init__.py
toolkit/_iter/__init__.pyi
toolkit/_iter/_mapping.py
toolkit/_iter/_sequence.py
toolkit/_serialization/__init__.py
toolkit/_serialization/__init__.pyi
toolkit/_serialization/_json.py
toolkit/_serialization/_main.py
toolkit/_serialization/_pydantic.py
toolkit/_serialization/_toml.py
toolkit/_serialization/_yaml.py
toolkit/_text/__init__.py
toolkit/_text/__init__.pyi
toolkit/_text/_strip_comments.py
toolkit/abc/__init__.py
toolkit/abc/__init__.pyi
toolkit/abc/_mapping.py
toolkit/abc/_sequence.py
toolkit/array/__init__.py
toolkit/array/__init__.pyi
toolkit/array/array_like/__init__.py
toolkit/array/array_like/__init__.pyi
toolkit/array/array_like/_bool.py
toolkit/array/array_like/_export.py
toolkit/array/array_like/_float.py
toolkit/array/array_like/_integer.py
toolkit/array/array_like/_types.py
toolkit/array/array_like/_utils.py
toolkit/array/jax/__init__.py
toolkit/array/jax/__init__.pyi
toolkit/array/jax/_bool.py
toolkit/array/jax/_export.py
toolkit/array/jax/_float.py
toolkit/array/jax/_integer.py
toolkit/array/jax/_utils.py
toolkit/array/numpy/__init__.py
toolkit/array/numpy/__init__.pyi
toolkit/array/numpy/_bool.py
toolkit/array/numpy/_export.py
toolkit/array/numpy/_float.py
toolkit/array/numpy/_integer.py
toolkit/array/numpy/_utils/__init__.py
toolkit/array/numpy/_utils/__init__.pyi
toolkit/array/numpy/_utils/_as_dtype.py
toolkit/array/numpy/_utils/_as_numpy.py
toolkit/array/numpy/_utils/_is.py
toolkit/array/numpy/_utils/_scale.py
toolkit/array/python/__init__.py
toolkit/array/python/__init__.pyi
toolkit/array/python/_cast.py
toolkit/array/torch/__init__.py
toolkit/array/torch/__init__.pyi
toolkit/array/torch/_bool.py
toolkit/array/torch/_export.py
toolkit/array/torch/_float.py
toolkit/array/torch/_integer.py
toolkit/array/torch/_utils.py
toolkit/environ/__init__.py
toolkit/environ/__init__.pyi
liblaf_toolkit-0.0.11.dist-info/METADATA
liblaf_toolkit-0.0.11.dist-info/WHEEL
liblaf_toolkit-0.0.11.dist-info/licenses/LICENSE
liblaf_toolkit-0.0.11.dist-info/RECORD
