Metadata-Version: 2.3
Name: liblaf-toolkit
Version: 0.0.11
Summary: Add your description here
Project-URL: Changelog, https://github.com/liblaf/python-toolkit/blob/main/CHANGELOG.md
Project-URL: Homepage, https://github.com/liblaf/python-toolkit
Project-URL: Issue Tracker, https://github.com/liblaf/python-toolkit/issues
Project-URL: Release Notes, https://github.com/liblaf/python-toolkit/releases
Project-URL: Source Code, https://github.com/liblaf/python-toolkit
Author-email: liblaf <30631553+liblaf@users.noreply.github.com>
Requires-Python: >=3.11
Requires-Dist: gitpython>=3.1.43
Requires-Dist: jaxtyping>=0.2.34
Requires-Dist: lazy-loader>=0.4
Requires-Dist: loguru>=0.7.2
Requires-Dist: pydantic-settings>=2.6.1
Requires-Dist: pydantic>=2.9.2
Requires-Dist: rich>=13.9.4
Requires-Dist: ruamel-yaml>=0.18.6
Requires-Dist: tomlkit>=0.13.2
Requires-Dist: tqdm>=4.66.5
Requires-Dist: ubelt>=1.3.6
Provides-Extra: comet
Requires-Dist: comet-ml>=3.47.2; extra == 'comet'
Provides-Extra: jax
Requires-Dist: jax>=0.4.35; extra == 'jax'
Provides-Extra: numpy
Requires-Dist: numpy>=2.1.3; extra == 'numpy'
Provides-Extra: torch
Requires-Dist: torch>=2.5.1; extra == 'torch'
